mvs/__init__.py
mvs/cli.py
mvs/constants.py
mvs/filesys.py
mvs/messages.py
mvs/optconfig.py
mvs/plan.py
mvs/problems.py
mvs/renaming.py
mvs/utils.py
mvs/version.py
mvs-2.0.0.dist-info/LICENSE
mvs-2.0.0.dist-info/METADATA
mvs-2.0.0.dist-info/WHEEL
mvs-2.0.0.dist-info/entry_points.txt
mvs-2.0.0.dist-info/top_level.txt
mvs-2.0.0.dist-info/RECORD
