Metadata-Version: 2.2
Name: mvs
Version: 2.0.0
Summary: Because one mv is rarely enough
Home-page: https://github.com/hindman/mvs
Author: Monty Hindman
Author-email: mhindman@gmail.com
License: MIT
Classifier: Development Status :: 5 - Production/Stable
Classifier: Environment :: Console
Classifier: Intended Audience :: Developers
Classifier: License :: OSI Approved :: MIT License
Classifier: Operating System :: OS Independent
Classifier: Programming Language :: Python :: 3.7
Classifier: Programming Language :: Python :: 3.8
Classifier: Programming Language :: Python :: 3.9
Classifier: Programming Language :: Python :: 3.10
Classifier: Programming Language :: Python :: 3.11
Classifier: Topic :: Software Development
Classifier: Topic :: System :: Shells
Classifier: Topic :: Terminals
Classifier: Topic :: Text Processing
Classifier: Topic :: Utilities
License-File: LICENSE
Requires-Dist: kwexception
Requires-Dist: pyperclip
Requires-Dist: short-con
Provides-Extra: test
Requires-Dist: pytest-cov; extra == "test"
Requires-Dist: tox; extra == "test"
Provides-Extra: dev
Requires-Dist: build; extra == "dev"
Requires-Dist: invoke; extra == "dev"
Requires-Dist: ipython; extra == "dev"
Requires-Dist: pycodestyle; extra == "dev"
Requires-Dist: twine; extra == "dev"
Requires-Dist: virtualenv; extra == "dev"
Requires-Dist: virtualenvwrapper; extra == "dev"
Dynamic: author
Dynamic: author-email
Dynamic: classifier
Dynamic: description
Dynamic: description-content-type
Dynamic: home-page
Dynamic: license
Dynamic: provides-extra
Dynamic: requires-dist
Dynamic: summary
